latex/vhdl/rom_m_mem_M.vhd
library IEEE;
use IEEE.STD_LOGIC_1164.ALL;


entity M is
	port(
		input : in std_logic_vector (0 to 7);
		output : out std_logic_vector (0 to 3)
	);
end M;

architecture dataflow of M is

begin
	output(0) <= input(0) and input(1);
	output(1) <= input(2) and input(3);
	output(2) <= input(4) and input(5);
	output(3) <= input(6) and input(7);
end dataflow;

2_1_ROM_M/2_1_ROM_M.srcs/sources_1/new/ROM.vhd
library IEEE;
use IEEE.STD_LOGIC_1164.ALL;
use IEEE.NUMERIC_STD.all;


entity ROM is
	port(
		address : in std_logic_vector(3 downto 0);
		data : out std_logic_vector(7 downto 0)
	);
end ROM;

architecture behavioral of ROM is

	type rom_16_8 is array (0 to 15) of std_logic_vector (0 to 7);
	signal rom : rom_16_8 := (x"A8", x"BD", x"17", x"E0",
							  x"C2", x"03", x"FF", x"46",
							  x"A8", x"BD", x"17", x"E0",
							  x"C2", x"03", x"FF", x"46");
	attribute rom_style : string;
	attribute rom_style of rom : signal is "block";
	
begin
	process(address)
	begin
		data <= ROM(to_integer(unsigned(address)));
	end process;
end behavioral;

2_2_ROM_M_BOARD/2_2_ROM_M_BOARD.srcs/sources_1/imports/new/S.vhd
library IEEE;
use IEEE.STD_LOGIC_1164.ALL;


entity S is
	port(
		input : in std_logic_vector (0 to 3);
		output: out std_logic_vector (0 to 3)
	);
end S;

architecture structural of S is
	signal data : std_logic_vector (0 to 7) := (others => '0');

	component ROM
	port(
		address : in std_logic_vector(3 downto 0);
		data : out std_logic_vector(7 downto 0)
	);
	end component;
	
	component M
	port(
		input : in std_logic_vector (0 to 7);
		output : out std_logic_vector (0 to 3)
	);
	end component;
	
begin
	rom_16_8 : ROM
	port map(
		address => input,
		data => data
	);
	
	m_comb : M
	port map(
		input => data,
		output => output
	);
end structural;

2_1_ROM_M/2_1_ROM_M.srcs/sim_1/new/S_tb.vhd
library IEEE;
use IEEE.STD_LOGIC_1164.ALL;
use IEEE.numeric_std.all;


entity S_tb is

end S_tb;

architecture behavioral of S_tb is
	component S
	port(
		input : in std_logic_vector (0 to 3);
		output: out std_logic_vector (0 to 3)
	);
	end component;
	
	component M
	port(
		input : in std_logic_vector (0 to 7);
		output : out std_logic_vector (0 to 3)
	);
	end component;
	
	signal input : std_logic_vector (0 to 3) := "0000";
	signal output : std_logic_vector (0 to 3) := "0000";
	signal test_input : std_logic_vector (0 to 7) := (others => '0');
	signal test_output : std_logic_vector (0 to 3) := "0000";
	type rom_16_8 is array (0 to 15) of std_logic_vector (0 to 7);
	signal data : rom_16_8 := (x"A8", x"BD", x"17", x"E0",
							   x"C2", x"03", x"FF", x"46",
							   x"A8", x"BD", x"17", x"E0",
							   x"C2", x"03", x"FF", x"46");
begin

	uut : S
	port map(
		input => input,
		output => output
	);
	
	reference_M : M 
	port map(
		input => test_input,
		output => test_output
	);
	
	stim_proc : process
	begin
		wait for 100 ns;
		for i in 0 to 15 loop
			input <= std_logic_vector(to_unsigned(i, 4));
			test_input <= data(i);
			wait for 10 ns;
			assert output = test_output
			report "Errore della macchina S per l'indirizzo " & integer'image(i)
			severity failure;
		end loop;
		wait;
	end process;
end behavioral;

latex/vcd/2_1_S_tb.vcd
$date
   Wed Mar  5 10:17:30 2025
$end
$version
  2023.1
$end
$timescale
  1ps
$end
$scope module S_tb $end
$var wire 4 ! input $end
$var wire 4 " output $end
$var wire 8 $ test_input $end
$var wire 4 % test_output $end
$upscope $end
$enddefinitions $end
#0
$dumpvars
b0 !
b0 "
b10101000 #
b0 $
b0 %
$end
#100000
b10101000 $
#110000
b110 "
b110 %
#120000
b1 "
b10111 #
b10111 $
b1 %
#130000
b1000 "
b11100000 #
b11100000 $
b1000 %
#150000
b1 "
b11 #
b11 $
b1 %
#160000
b1111 "
b11111111 #
b11111111 $
b1111 %
#170000
b0 "
b1000110 #
b1000110 $
b0 %
#180000
b1000 !
b10101000 #
b10101000 $
#190000
b110 "
b110 %
#200000
b1 "
b10111 #
b10111 $
b1 %
#210000
b1000 "
b11100000 #
b11100000 $
b1000 %
#230000
b1 "
b11 #
b11 $
b1 %
#240000
b1111 "
b11111111 #
b11111111 $
b1111 %
#250000
b0 "
b1000110 #
b1000110 $
b0 %
