latex/vhdl/Sequence_Detector.vhd
library IEEE;
use IEEE.STD_LOGIC_1164.ALL;


entity Sequence_Detector is
port (
	input : in std_logic;
	M : in std_logic;
	reset : in std_logic;
	clock: in std_logic;
	A : in std_logic;
	state_output_led : out std_logic_vector(0 to 6);
	Y : out std_logic
);
end Sequence_Detector;

architecture behavioral of Sequence_Detector is
	signal current_mode : std_logic := '0';
	type stato is (S0, S1, S2, S3, S4, S5, S6);
	signal current_state : stato := S0;
	attribute fsm_encoding : string;
	attribute fsm_encoding of current_state : signal is "one_hot";
begin
	sequence_detector : process(clock)
	begin
		if clock'event and clock = '1' then
			if reset = '1' or current_mode /= M then
				state_output_led <= "0000001";
				current_state <= S0;
				Y <= '0';
				current_mode <= M;
			elsif A = '1' then
				case current_state is
					when S0 =>
						if current_mode = '0' then
							if input = '0' then
								state_output_led <= "0000100";
								current_state <= S2;
							else
								state_output_led <= "0000010";
								current_state <= S1;
							end if;
						else
							if input = '0' then
								state_output_led <= "0000001";
								current_state <= S0;
							else
								state_output_led <= "0100000";
								current_state <= S5;
							end if;
						end if;
						Y <= '0';
					when S1 =>
						if input = '0' then
							state_output_led <= "0001000";
							current_state <= S3;
						else
							state_output_led <= "0010000";
							current_state <= S4;
						end if;
						Y <= '0';
					when S2 =>
						state_output_led <= "0010000";
						current_state <= S4;
						Y <= '0';
					when S3 =>
						state_output_led <= "0000001";
						current_state <= S0;
						Y <= input;
					when S4 =>
						state_output_led <= "0000001";
						current_state <= S0;
						Y <= '0';
					when S5 =>
						if input = '0' then
							state_output_led <= "1000000";
							current_state <= S6;
						else
							state_output_led <= "0100000";
							current_state <= S5;
						end if;
						Y <= '0';
					when S6 =>
						state_output_led <= "0000001";
						current_state <= S0;
						Y <= input;
				end case;
			end if;
		end if;
	end process;
end behavioral;

latex/vhdl/Sequence_Detector_tb.vhd
library IEEE;
use IEEE.STD_LOGIC_1164.ALL;


entity Sequence_Detector_tb is

end Sequence_Detector_tb;

architecture behavioral of Sequence_Detector_tb is
	component Sequence_Detector
	port (
		input : in std_logic;
		M : in std_logic;
		reset : in std_logic;
		clock: in std_logic;
		A : in std_logic;
		state_output_led : out std_logic_vector(0 to 6);
		Y : out std_logic
	);
	end component;
	
	constant CLK_period : time := 10 ns;
	
	signal input : std_logic := '0';
	signal M : std_logic := '0';
	signal reset : std_logic := '1';
	signal clock : std_logic := '0';
	signal enable : std_logic := '0';
	signal output : std_logic := '0';
begin
	
	uut : Sequence_Detector
	port map(
		input => input,
		M => M,
		reset => reset,
		clock => clock,
		A => enable,
		Y => output
	);
	
	CLK_process :process
	begin
		clock <= '0';
		wait for CLK_period/2;
		clock <= '1';
		wait for CLK_period/2;
	end process;
	
	stim_process : process
	begin
		wait for 100ns;
		enable <= '1';
		reset <= '0';
		input <= '0';
		wait for 10 ns;
		input <= '0';
		wait for 10 ns;
		input <= '0';
		wait for 10 ns;
		input <= '1';
		wait for 10 ns;
		input <= '0';
		wait for 10 ns;
		input <= '1';
		wait for 10 ns;
		assert output = '1'
		report "Errore del riconoscitore in modalità M = 0"
		severity failure;
		
		wait for 10 ns;
		M <= '1';
		input <= '0';
		wait for 10 ns;
		input <= '0';
		wait for 10 ns;
		input <= '0';
		wait for 10ns;
		input <= '1';
		wait for 10ns;
		input <= '1';
		wait for 10 ns;
		input <= '0';
		wait for 10 ns;
		input <= '1';
		wait for 10ns;
		assert output = '1'
		report "Errore del riconoscitore in modalità M = 0"
		severity failure;
		
		wait;
	end process;
end behavioral;

latex/vcd/sequence_detector_tb.vcd
$date
   Thu Mar  6 11:01:44 2025
$end
$version
  2023.1
$end
$timescale
  1ps
$end
$scope module Sequence_Detector_tb $end
$var wire 1 ! input $end
$var wire 1 " M $end
$var wire 1 # reset $end
$var wire 1 $ clock $end
$var wire 1 % enable $end
$var wire 1 ' output $end
$upscope $end
$enddefinitions $end
#0
$dumpvars
0!
0"
1#
0$
0%
bx &
x'
0(
$end
#5000
1$
b1 &
#10000
0$
#15000
1$
#20000
0$
#25000
1$
#30000
0$
#35000
1$
#40000
0$
#45000
1$
#50000
0$
#55000
1$
#60000
0$
#65000
1$
#70000
0$
#75000
1$
#80000
0$
#85000
1$
#90000
0$
#95000
1$
#100000
0#
0$
1%
#105000
1$
b100 &
#110000
0$
#115000
1$
b10000 &
#120000
0$
#125000
1$
#130000
1!
0$
#135000
1$
#140000
0!
0$
#145000
1$
#150000
1!
0$
#155000
1$
1'
#160000
0$
#165000
1$
0'
#170000
0!
1"
0$
#175000
1$
1(
#180000
0$
#185000
1$
#190000
0$
#195000
1$
#200000
1!
0$
#205000
1$
#210000
0$
#215000
1$
#220000
0!
0$
#225000
1$
b1000000 &
#230000
1!
0$
#235000
1$
b1 &
1'
#240000
0$
#245000
1$
0'
