1_2_INTERCONNECTION_16_4/1_2_INTERCONNECTION_16_4.srcs/sources_1/imports/new/mux4_1.vhd
library IEEE;
use IEEE.STD_LOGIC_1164.ALL;


entity mux4_1 is
	port(
		a : in std_logic_vector(0 to 3);
		s : in std_logic_vector(1 downto 0);
		y : out std_logic 
	);
end mux4_1;

architecture dataflow of mux4_1 is
begin
	with s select
		y <=	a(0) when "00",
				a(1) when "01",
				a(2) when "10",
				a(3) when "11",
				'-' when others;
end dataflow;

latex/vhdl/mux16_1.vhd
library IEEE;
use IEEE.STD_LOGIC_1164.ALL;


entity mux16_1 is
	port(
		a : in std_logic_vector(0 to 15);
		s : in std_logic_vector(3 downto 0);
		y : out std_logic 
	);
end mux16_1;

architecture structural of mux16_1 is
	signal u : std_logic_vector(0 to 3) := "0000";
	
	component mux4_1
	port(
		a : in std_logic_vector(0 to 3);
		s : in std_logic_vector(1 downto 0);
		y : out std_logic
	);
	end component;

begin
	mux0 : mux4_1
	port map(
		a => a(0 to 3),
		s => s(1 downto 0),
		y => u(0)
	);
	mux1 : mux4_1
	port map(
		a => a(4 to 7),
		s => s(1 downto 0),
		y => u(1)
	);
	mux2 : mux4_1
	port map(
		a => a(8 to 11),
		s => s(1 downto 0),
		y => u(2)
	);
	mux3 : mux4_1
	port map(
		a => a(12 to 15),
		s => s(1 downto 0),
		y => u(3)
	);
	mux4 : mux4_1
	port map(
		a => u,
		s => s(3 downto 2),
		y => y
	);
end structural;

1_1_MUX_16_1/1_1_MUX_16_1.srcs/sim_1/new/mux16_1_tb.vhd
library IEEE;
use IEEE.STD_LOGIC_1164.ALL;
use IEEE.NUMERIC_STD.all;


entity mux16_1_tb is

end mux16_1_tb;

architecture behavioral of mux16_1_tb is
	
	component mux16_1
	port(
		a : in std_logic_vector(0 to 15);
		s : in std_logic_vector(3 downto 0);
		y : out std_logic
	); 
	end component; 

	signal input 	: std_logic_vector (0 to 15) := (others => '0');
	signal control 	: std_logic_vector (3 downto 0) := (others => '0');
	signal output 	: STD_LOGIC := '0';

begin
	uut: mux16_1 
		port map(
			a => input,
			s => control,
			y => output
		);

	stim_proc: process
	begin
		wait for 100 ns;
		input 	<= "1010110111100011";
		
		for i in 0 to 15 loop
			control <= std_logic_vector(to_unsigned(i, 4));
			wait for 10 ns;
			assert output = input(i) report "Errore nella selezione dell'ingresso " & integer'image(i) severity failure;
		end loop;
		wait;
	end process;
end behavioral;

1_1_MUX_16_1/1_1_MUX_16_1.sim/sim_1/behav/xsim/dump.vcd
$date
   Tue Mar  4 03:06:30 2025
$end
$version
  2023.1
$end
$timescale
  1ps
$end
$scope module mux16_1_tb $end
$var wire 16 ! input $end
$var wire 4 " control $end
$var wire 1 # output $end
$upscope $end
$enddefinitions $end
#0
$dumpvars
b0 !
b0 "
0#
b0 $
b0 %
b0 &
0'
b0 (
0)
b0 *
0+
b0 ,
0-
b0 .
$end
#100000
b1010110111100011 !
1#
b1110 $
b1010 %
1'
b1101 (
b1110 *
1+
b11 ,
#120000
0#
b110 $
0'
#140000
1#
b1011 $
1'
0)
1-
#160000
0#
b101 $
0'
#180000
1#
b1110 $
1'
1+
#200000
b110 $
0'
#220000
0#
b1011 $
1'
0)
1-
#240000
1#
b101 $
0'
#260000
b1000 "
1#
b1110 $
b0 &
1'
1+
b10 .
#280000
b110 $
0'
#300000
b1011 $
1'
0)
1-
#320000
0#
b101 $
0'
#340000
0#
b1110 $
1'
1+
#360000
b110 $
0'
#380000
1#
b1011 $
1'
0)
1-
#400000
b101 $
0'
